odoo/addons/test_base_tier_validation/README.rst
odoo/addons/test_base_tier_validation/__init__.py
odoo/addons/test_base_tier_validation/__manifest__.py
odoo/addons/test_base_tier_validation/demo/tier_definition.xml
odoo/addons/test_base_tier_validation/i18n/test_base_tier_validation.pot
odoo/addons/test_base_tier_validation/models/__init__.py
odoo/addons/test_base_tier_validation/models/res_partner.py
odoo/addons/test_base_tier_validation/models/tier_definition.py
odoo/addons/test_base_tier_validation/readme/CONTRIBUTORS.rst
odoo/addons/test_base_tier_validation/readme/DESCRIPTION.rst
odoo/addons/test_base_tier_validation/static/description/icon.png
odoo/addons/test_base_tier_validation/static/description/index.html
odoo/addons/test_base_tier_validation/views/res_partner_view.xml
odoo14_addon_test_base_tier_validation-14.0.1.0.2.dist-info/METADATA
odoo14_addon_test_base_tier_validation-14.0.1.0.2.dist-info/WHEEL
odoo14_addon_test_base_tier_validation-14.0.1.0.2.dist-info/top_level.txt
odoo14_addon_test_base_tier_validation-14.0.1.0.2.dist-info/RECORD
